graph_notebook/__init__.py
graph_notebook/start_jupyterlab.py
graph_notebook/start_notebook.py
graph_notebook/configuration/__init__.py
graph_notebook/configuration/generate_config.py
graph_notebook/configuration/get_config.py
graph_notebook/decorators/__init__.py
graph_notebook/decorators/decorators.py
graph_notebook/ipython_profile/__init__.py
graph_notebook/ipython_profile/configure_ipython_profile.py
graph_notebook/jupyter_profile/__init__.py
graph_notebook/jupyter_profile/jupyter_notebook_config.py
graph_notebook/magics/__init__.py
graph_notebook/magics/graph_magic.py
graph_notebook/magics/metadata.py
graph_notebook/magics/ml.py
graph_notebook/magics/streams.py
graph_notebook/magics/completers/__init__.py
graph_notebook/magics/completers/graph_completer.py
graph_notebook/magics/parsing/__init__.py
graph_notebook/magics/parsing/replace_namespace_vars.py
graph_notebook/nbextensions/__init__.py
graph_notebook/nbextensions/install.py
graph_notebook/nbextensions/gremlin_syntax/__init__.py
graph_notebook/nbextensions/gremlin_syntax/static/README.md
graph_notebook/nbextensions/gremlin_syntax/static/__init__.py
graph_notebook/nbextensions/gremlin_syntax/static/description.yaml
graph_notebook/nbextensions/gremlin_syntax/static/main.js
graph_notebook/nbextensions/neptune_menu/__init__.py
graph_notebook/nbextensions/neptune_menu/static/README.md
graph_notebook/nbextensions/neptune_menu/static/__init__.py
graph_notebook/nbextensions/neptune_menu/static/description.yaml
graph_notebook/nbextensions/neptune_menu/static/main.js
graph_notebook/nbextensions/opencypher_syntax/__init__.py
graph_notebook/nbextensions/opencypher_syntax/static/README.md
graph_notebook/nbextensions/opencypher_syntax/static/__init__.py
graph_notebook/nbextensions/opencypher_syntax/static/description.yaml
graph_notebook/nbextensions/opencypher_syntax/static/main.js
graph_notebook/nbextensions/playable_cells/__init__.py
graph_notebook/nbextensions/playable_cells/static/README.md
graph_notebook-5.0.2.dist-info/METADATA
graph_notebook-5.0.2.dist-info/WHEEL
graph_notebook-5.0.2.dist-info/entry_points.txt
graph_notebook-5.0.2.dist-info/licenses/LICENSE
graph_notebook-5.0.2.dist-info/licenses/NOTICE
graph_notebook-5.0.2.dist-info/RECORD
