Metadata-Version: 2.4
Name: graph-notebook
Version: 5.0.2
Summary: Jupyter notebook extension to connect to graph databases
Author-email: amazon-neptune <amazon-neptune-pypi@amazon.com>
License: 
License-File: LICENSE
License-File: NOTICE
Keywords: gremlin,jupyter,neptune,opencypher,sparql
Classifier: Development Status :: 5 - Production/Stable
Classifier: License :: OSI Approved :: Apache Software License
Classifier: Programming Language :: Python :: 3.9
Classifier: Programming Language :: Python :: 3.10
Classifier: Programming Language :: Python :: 3.11
Requires-Python: <3.12,>=3.9
Requires-Dist: async-timeout<5.0,>=4.0
Requires-Dist: boto3>=1.34.74
Requires-Dist: botocore>=1.34.74
Requires-Dist: gremlinpython<=3.7.2,>=3.5.1
Requires-Dist: ipyfilechooser==0.6.0
Requires-Dist: ipykernel>=6.5.0
Requires-Dist: ipython<=8.10.0,>=7.16.1
Requires-Dist: ipywidgets<9.0.0,>=8.0.0
Requires-Dist: itables<=2.1.0,>=2.0.0
Requires-Dist: jedi<=0.18.2,>=0.18.1
Requires-Dist: jinja2<=3.1.4,>=3.0.3
Requires-Dist: json-repair==0.29.2
Requires-Dist: jupyter-client<9.0.0,>=8.0.0
Requires-Dist: jupyter-server-proxy<5.0.0,>=4.0.0
Requires-Dist: jupyter-server<3.0.0,>=2.0.0
Requires-Dist: jupyterlab-widgets<4.0.0,>=3.0.0
Requires-Dist: jupyterlab<5.0.0,>=4.3.5
Requires-Dist: nbclassic>=1.3.0
Requires-Dist: nbclient>=0.7.3
Requires-Dist: nbconvert<=7.2.8,>=6.3.0
Requires-Dist: neo4j<=5.23.1,>=5.0.0
Requires-Dist: nest-asyncio<=1.6.0,>=1.5.5
Requires-Dist: networkx==2.4
Requires-Dist: notebook<8.0.0,>=7.0.0
Requires-Dist: numba==0.60.0
Requires-Dist: numpy<1.24.0,>=1.23.5
Requires-Dist: pandas<=2.2.2,>=2.1.0
Requires-Dist: rdflib==7.0.0
Requires-Dist: requests<=2.32.2,>=2.32.0
Requires-Dist: sparqlwrapper==2.0.0
Provides-Extra: test
Requires-Dist: pytest==6.2.5; extra == 'test'
